2025_assignment2_vaultpasswordmanager-2.1.0.dist-info/licenses/LICENSE
dynapyt_analysis/__init__.py
dynapyt_analysis/trace.py
lib/Config.py
lib/Encryption.py
lib/__init__.py
models/Category.py
models/Secret.py
models/User.py
models/__init__.py
models/base.py
modules/__init__.py
modules/autocomplete.py
modules/carry.py
modules/misc.py
perftest/__init__.py
perftest/test_performance.py
tools/__init__.py
tools/dynapyt_driver.py
tools/troubleshoot_db.py
unittest/__init__.py
unittest/base.py
unittest/test_vault.py
unittest/lib/__init__.py
unittest/lib/test_Config.py
unittest/lib/test_Encryption.py
unittest/models/__init__.py
unittest/models/test_Category.py
unittest/models/test_Secret.py
unittest/models/test_User.py
unittest/models/test_base.py
unittest/modules/__init__.py
unittest/modules/test_autocomplete.py
unittest/modules/test_carry.py
unittest/modules/test_misc.py
unittest/tools/__init__.py
unittest/tools/test_troubleshoot_db.py
unittest/views/__init__.py
unittest/views/test_categories.py
unittest/views/test_change_key.py
unittest/views/test_clipboard.py
unittest/views/test_import_export.py
unittest/views/test_menu.py
unittest/views/test_migration.py
unittest/views/test_secrets.py
unittest/views/test_setup.py
unittest/views/test_users.py
views/__init__.py
views/categories.py
views/change_key.py
views/clipboard.py
views/import_export.py
views/menu.py
views/migration.py
views/secrets.py
views/setup.py
views/users.py
2025_assignment2_vaultpasswordmanager-2.1.0.dist-info/METADATA
2025_assignment2_vaultpasswordmanager-2.1.0.dist-info/WHEEL
2025_assignment2_vaultpasswordmanager-2.1.0.dist-info/entry_points.txt
2025_assignment2_vaultpasswordmanager-2.1.0.dist-info/top_level.txt
2025_assignment2_vaultpasswordmanager-2.1.0.dist-info/RECORD
