Metadata-Version: 2.4
Name: 2025_assignment2_vaultPasswordManager
Version: 2.1.0
Summary: Python Password Manager
Home-page: https://gitlab.com/mbroglio/2025_assignment2_vaultPasswordManager
Author: EmacsSoftwares
Author-email: matteo.broglio3@gmail.com
License: MIT
Classifier: Topic :: Security
Classifier: Topic :: Security :: Cryptography
Classifier: License :: OSI Approved :: MIT License
Classifier: Operating System :: MacOS
Classifier: Operating System :: POSIX :: Linux
Classifier: Natural Language :: English
Classifier: Programming Language :: Python :: 3
Classifier: Programming Language :: Python
License-File: LICENSE
Requires-Dist: pycryptodome==3.20.0
Requires-Dist: pyperclip
Requires-Dist: tabulate
Requires-Dist: passwordgenerator
Requires-Dist: SQLAlchemy==1.4.41
Requires-Dist: sqlcipher3==0.5.4
Dynamic: license-file
